Metadata-Version: 1.0
Name: wsmocky
Version: 0.1.6
Summary: Create dynamic mock server with wsdl file.
Home-page: https://github.com/ipconfiger/wsmocky
Author: Alexander.Li
Author-email: superpowerlee@gmail.com
License: MIT
Keywords: webservice mock
Platform: UNKNOWN
